ddesigner_api/__init__.py
ddesigner_api/numpy/__init__.py
ddesigner_api/numpy/examples/__init__.py
ddesigner_api/numpy/examples/examples_numpy.py
ddesigner_api/numpy/xwn/__init__.py
ddesigner_api/numpy/xwn/functions.py
ddesigner_api/numpy/xwn/optimization.py
ddesigner_api/pytorch/__init__.py
ddesigner_api/pytorch/dpi_nn.py
ddesigner_api/pytorch/examples/__init__.py
ddesigner_api/pytorch/examples/examples_pytorch.py
ddesigner_api/pytorch/xwn/__init__.py
ddesigner_api/pytorch/xwn/torch_nn.py
ddesigner_api/pytorch/xwn/torch_opt.py
ddesigner_api/tensorflow/__init__.py
ddesigner_api/tensorflow/dpi_blocks.py
ddesigner_api/tensorflow/dpi_layers.py
ddesigner_api/tensorflow/examples/__init__.py
ddesigner_api/tensorflow/examples/examples_keras.py
ddesigner_api/tensorflow/examples/examples_tensorflow.py
ddesigner_api/tensorflow/xwn/__init__.py
ddesigner_api/tensorflow/xwn/base_conv.py
ddesigner_api/tensorflow/xwn/keras_layers.py
ddesigner_api/tensorflow/xwn/keras_opt.py
ddesigner_api/tensorflow/xwn/tf_nn.py
ddesigner_api/tensorflow/xwn/tf_opt.py
DDesignerAPI-0.0.6.2.dist-info/LICENSE
DDesignerAPI-0.0.6.2.dist-info/METADATA
DDesignerAPI-0.0.6.2.dist-info/WHEEL
DDesignerAPI-0.0.6.2.dist-info/top_level.txt
DDesignerAPI-0.0.6.2.dist-info/RECORD
