Metadata-Version: 2.1
Name: DDesignerAPI
Version: 0.0.6.2
Summary: Deep-learning Designer: Deep-Learning Training Optimization & Layers API(like Keras)
Home-page: https://github.com/DPI/DDesigner
Author: Deeper-I
Author-email: dean@deeper-i.com
License: Apache-2.0, BSD3-Clause
Keywords: xwn,pytorch,tensorflow,keras
Platform: UNKNOWN
Classifier: Programming Language :: Python :: 3.7
Requires-Python: >=3.7
